{"GXD4IWEsIpJeMJ3o2byh7Q==":"logo-marssun-v2b-white-397x148.png","hAV4gc67Kc+VTfK7kdMCdA==":"logo-marssun-v2b-1116x416.png","703jGkvtoXpxbZTG7S89UA==":"features2.jpg","WeIcOp+qLfFEPxVAXUUAEA==":"features4.jpg","Vb7GgbMoe0curpGYBParsg==":"background3.jpg","HUfpc9SvDwBk7sbVG2SgiA==":"features3.jpg","Cesjxe6cW0NYFSAP4kiRig==":"features1.jpg","qvfrZyIxC58gWq06L4fvUA==":"planet1-2000x1250.jpg","3LXXzRZe5+kg/rhiA6ALOA==":"banner1-2000x810.jpg","kjCjXumzG5TpI4+piFEdoA==":"chip-pic1-2000x1125.jpg","rTnB5kFCuXdPKKac1m8L2Q==":"back-mars-1929x1233.png","5/qkaia1g1++ltZZdVEtDQ==":"siren-talk1-1-598x298.jpeg","NXWq6/eco8qzPOmWecxzjw==":"smart-aircon-598x377.jpeg","Ek35Ch9MjHsfux086jTP3A==":"image11-small-296x296.jpeg","HKMffZYvGodjhCDycTNGvw==":"ai-concept-598x336.jpeg","3hR0vxtugBCVfFqqQdpgiA==":"ai-concept-1-598x336.jpeg","JnpBqfvrV1bdHMHdzz4/8Q==":"1698%20copy-598x486.jpeg","uhoSVQJ651dx/Q/J/Aai2Q==":"vias-video-1-1256x707.jpeg","nZ/AFuK3mZsMx5roGZZntw==":"office-scenario-1256x707.jpeg","ekDw/IKIqDosr2bhfbZFmw==":"safe-home-596x370.jpeg","DCBf9g2deTmi1WmdNSPJHA==":"safe-home-1-596x370.jpeg"}